{
  "id": 11,
  "totalTrades": 72,
  "level": 71,
  "weeklyFlowerSpent": 0,
  "weeklyFlowerEarned": 0,
  "tokenUri": "0_v1_306_90_52_62_234_89_226_475_29_514_86_0_276_72_0_266",
  "username": "rafael",
  "listings": {},
  "friends": [
    {
      "id": 200655,
      "tokenUri": "0_v1_32_2_184_0_234_89_44_475_0_0_0_483",
      "username": "Curiles",
      "trades": 2
    },
    {
      "id": 1750540559978793,
      "tokenUri": "0_v1_48_1_43_13_234_89_23_125_0_0_0_458",
      "username": "Panda18",
      "trades": 2
    },
    {
      "id": 48660,
      "tokenUri": "0_v1_71_1_63_0_0_22_226_81_0_0_0_0_267_73_0_266",
      "username": "Kerim",
      "trades": 2
    },
    {
      "id": 8716851572060369,
      "tokenUri": "0_v1_47_1_52_88_234_89_240_475_0_0_86_483_451",
      "username": "Muoi",
      "trades": 2
    },
    {
      "id": 144839,
      "tokenUri": "0_v1_48_2_51_342_46_22_23_395_0_0_0_0_451_0_0_266",
      "username": "dikaa",
      "trades": 1
    }
  ],
  "trades": [
    {
      "id": "35fb2ea7",
      "sfl": 4.695,
      "quantity": 75,
      "itemId": 603,
      "collection": "collectibles",
      "source": "listing",
      "fulfilledAt": 1767879486844,
      "initiatedBy": {
        "id": 6789792581946775,
        "bumpkinUri": "0_v1_32_1_5_282_234_22_240_517_0_0_0_0_0_0_0_177",
        "username": "Kael2050"
      },
      "fulfilledBy": {
        "id": 11,
        "bumpkinUri": "0_v1_306_90_52_62_234_89_226_475_29_514_86_0_276_72_0_266",
        "username": "rafael"
      }
    },
    {
      "id": "a856b6ca",
      "sfl": 7.59,
      "quantity": 100,
      "itemId": 741,
      "collection": "collectibles",
      "source": "listing",
      "fulfilledAt": 1757892981802,
      "initiatedBy": {
        "id": 54221,
        "bumpkinUri": "0_v1_48_2_184_342_234_34_226_25_0_0_86_0_450",
        "username": "Ayagba"
      },
      "fulfilledBy": {
        "id": 11,
        "bumpkinUri": "0_v1_306_90_52_62_234_89_226_475_29_514_86_0_276_72_0_266",
        "username": "rafael"
      }
    },
    {
      "id": "3d2f6810",
      "sfl": 4.9,
      "quantity": 15,
      "itemId": 641,
      "collection": "collectibles",
      "source": "listing",
      "fulfilledAt": 1757501019402,
      "initiatedBy": {
        "id": 11,
        "bumpkinUri": "0_v1_306_90_52_62_234_89_226_475_29_514_86_0_276_72_0_266",
        "username": "rafael"
      },
      "fulfilledBy": {
        "id": 8756237900509771,
        "bumpkinUri": "0_v1_364_90_6_459_338_339_226_395_285_311_16_251_0_189",
        "username": "Vachelet"
      }
    },
    {
      "id": "f3345fa8",
      "sfl": 7.29,
      "quantity": 10,
      "itemId": 267,
      "collection": "collectibles",
      "source": "listing",
      "fulfilledAt": 1756381071175,
      "initiatedBy": {
        "id": 15185,
        "bumpkinUri": "0_v1_55_263_74_325_327_65_400_293_30_382_0_0_0_277",
        "username": "pibound"
      },
      "fulfilledBy": {
        "id": 11,
        "bumpkinUri": "0_v1_306_90_52_62_234_89_226_475_29_514_86_0_276_72_0_266",
        "username": "rafael"
      }
    },
    {
      "id": "12a30423",
      "sfl": 5.5109,
      "quantity": 4,
      "itemId": 266,
      "collection": "collectibles",
      "source": "listing",
      "fulfilledAt": 1756381058179,
      "initiatedBy": {
        "id": 7872720949259591,
        "bumpkinUri": "0_v1_48_1_5_13_18_22_23_395_0_0_0_458",
        "username": "Azzura aisyah"
      },
      "fulfilledBy": {
        "id": 11,
        "bumpkinUri": "0_v1_306_90_52_62_234_89_226_475_29_514_86_0_276_72_0_266",
        "username": "rafael"
      }
    },
    {
      "id": "dab1a42a",
      "sfl": 2.057,
      "quantity": 11,
      "itemId": 614,
      "collection": "collectibles",
      "source": "listing",
      "fulfilledAt": 1756360259976,
      "initiatedBy": {
        "id": 85642,
        "bumpkinUri": "0_v1_47_3_7_15_404_22_23",
        "username": "DarkAngel"
      },
      "fulfilledBy": {
        "id": 11,
        "bumpkinUri": "0_v1_306_90_52_62_234_89_226_475_29_514_86_0_276_72_0_266",
        "username": "rafael"
      }
    },
    {
      "id": "0be4f241",
      "sfl": 1.122,
      "quantity": 6,
      "itemId": 614,
      "collection": "collectibles",
      "source": "listing",
      "fulfilledAt": 1756360245150,
      "initiatedBy": {
        "id": 264849729428878,
        "bumpkinUri": "0_v1_32_1_7_13_19_41_44_476_0_0_0_0_451",
        "username": "Rv3"
      },
      "fulfilledBy": {
        "id": 11,
        "bumpkinUri": "0_v1_306_90_52_62_234_89_226_475_29_514_86_0_276_72_0_266",
        "username": "rafael"
      }
    },
    {
      "id": "8b6b6c1f",
      "sfl": 25.5897,
      "quantity": 100,
      "itemId": 641,
      "collection": "collectibles",
      "source": "listing",
      "fulfilledAt": 1756341985557,
      "initiatedBy": {
        "id": 177120,
        "bumpkinUri": "0_v1_460_140_63_286_20_34_455_376_457_433_0_0_453_430_0_177_516",
        "username": "Solomon"
      },
      "fulfilledBy": {
        "id": 11,
        "bumpkinUri": "0_v1_306_90_52_62_234_89_226_475_29_514_86_0_276_72_0_266",
        "username": "rafael"
      }
    },
    {
      "id": "7aa9285b",
      "sfl": 12.264,
      "quantity": 30,
      "itemId": 253,
      "collection": "collectibles",
      "source": "listing",
      "fulfilledAt": 1756220076551,
      "initiatedBy": {
        "id": 3949,
        "bumpkinUri": "0_v1_53_485_487_353_359_89_167_163_30_0_0_0_494_175",
        "username": "Tinebrindir"
      },
      "fulfilledBy": {
        "id": 11,
        "bumpkinUri": "0_v1_306_90_52_62_234_89_226_475_29_514_86_0_276_72_0_266",
        "username": "rafael"
      }
    },
    {
      "id": "a05d0860",
      "sfl": 7.0176,
      "quantity": 300,
      "itemId": 210,
      "collection": "collectibles",
      "source": "listing",
      "fulfilledAt": 1756169884458,
      "initiatedBy": {
        "id": 2004400689125008,
        "bumpkinUri": "0_v1_348_90_5_342_18_22_445_125_0_0_0_0_451",
        "username": "MANDRAGORA"
      },
      "fulfilledBy": {
        "id": 11,
        "bumpkinUri": "0_v1_306_90_52_62_234_89_226_475_29_514_86_0_276_72_0_266",
        "username": "rafael"
      }
    },
    {
      "id": "583522e1",
      "sfl": 2.1,
      "quantity": 1,
      "itemId": 239,
      "collection": "collectibles",
      "source": "listing",
      "fulfilledAt": 1755972371001,
      "initiatedBy": {
        "id": 9005253740336645,
        "bumpkinUri": "0_v1_32_1_202_85_234_89_44_517_0_0_86_117",
        "username": "Lunafreya"
      },
      "fulfilledBy": {
        "id": 11,
        "bumpkinUri": "0_v1_306_90_52_62_234_89_226_475_29_514_86_0_276_72_0_266",
        "username": "rafael"
      }
    },
    {
      "id": "12392c62",
      "sfl": 6.54,
      "quantity": 200,
      "itemId": 216,
      "collection": "collectibles",
      "source": "listing",
      "fulfilledAt": 1755933969503,
      "initiatedBy": {
        "id": 18604,
        "bumpkinUri": "0_v1_57_90_52_317_234_339_162_128_30_383_86_0_450_440_0_266",
        "username": "BilkNoggin"
      },
      "fulfilledBy": {
        "id": 11,
        "bumpkinUri": "0_v1_306_90_52_62_234_89_226_475_29_514_86_0_276_72_0_266",
        "username": "rafael"
      }
    },
    {
      "id": "b05f7c0a",
      "sfl": 6.54,
      "quantity": 200,
      "itemId": 216,
      "collection": "collectibles",
      "source": "listing",
      "fulfilledAt": 1755933965198,
      "initiatedBy": {
        "id": 72882,
        "bumpkinUri": "0_v1_53_193_74_195_20_22_488_163_0_0_0_0_159",
        "username": "Hyrioku"
      },
      "fulfilledBy": {
        "id": 11,
        "bumpkinUri": "0_v1_306_90_52_62_234_89_226_475_29_514_86_0_276_72_0_266",
        "username": "rafael"
      }
    },
    {
      "id": "fa80b02b",
      "sfl": 3.6713,
      "quantity": 250,
      "itemId": 256,
      "collection": "collectibles",
      "source": "listing",
      "fulfilledAt": 1755933875987,
      "initiatedBy": {
        "id": 3722,
        "bumpkinUri": "0_v1_32_90_6_282_234_34_226_475_0_228_0_350",
        "username": "BestPrices"
      },
      "fulfilledBy": {
        "id": 11,
        "bumpkinUri": "0_v1_306_90_52_62_234_89_226_475_29_514_86_0_276_72_0_266",
        "username": "rafael"
      }
    },
    {
      "id": "38853355",
      "sfl": 3.5986,
      "quantity": 22,
      "itemId": 614,
      "collection": "collectibles",
      "source": "listing",
      "fulfilledAt": 1755911902639,
      "initiatedBy": {
        "id": 6199938390503589,
        "bumpkinUri": "0_v1_0_1_42_14_19_22_44_395_0_0_0_458_451",
        "username": "BoyNegro"
      },
      "fulfilledBy": {
        "id": 11,
        "bumpkinUri": "0_v1_306_90_52_62_234_89_226_475_29_514_86_0_276_72_0_266",
        "username": "rafael"
      }
    },
    {
      "id": "67915420",
      "sfl": 0.9813,
      "quantity": 6,
      "itemId": 614,
      "collection": "collectibles",
      "source": "listing",
      "fulfilledAt": 1755911896413,
      "initiatedBy": {
        "id": 7580774000399633,
        "bumpkinUri": "0_v1_32_1_5_13_18_22_23_476_0_0_0_0_451",
        "username": "obit0"
      },
      "fulfilledBy": {
        "id": 11,
        "bumpkinUri": "0_v1_306_90_52_62_234_89_226_475_29_514_86_0_276_72_0_266",
        "username": "rafael"
      }
    },
    {
      "id": "e784b21e",
      "sfl": 2.1707,
      "quantity": 12,
      "itemId": 614,
      "collection": "collectibles",
      "source": "listing",
      "fulfilledAt": 1755785430165,
      "initiatedBy": {
        "id": 4419015691059773,
        "bumpkinUri": "0_v1_48_90_49_88_404_89_23_91",
        "username": "Inchang"
      },
      "fulfilledBy": {
        "id": 11,
        "bumpkinUri": "0_v1_306_90_52_62_234_89_226_475_29_514_86_0_276_72_0_266",
        "username": "rafael"
      }
    },
    {
      "id": "49779c05",
      "sfl": 0.9042,
      "quantity": 5,
      "itemId": 614,
      "collection": "collectibles",
      "source": "listing",
      "fulfilledAt": 1755785426409,
      "initiatedBy": {
        "id": 1360,
        "bumpkinUri": "0_v1_32_90_42_88_234_34_210_395",
        "username": "Knight"
      },
      "fulfilledBy": {
        "id": 11,
        "bumpkinUri": "0_v1_306_90_52_62_234_89_226_475_29_514_86_0_276_72_0_266",
        "username": "rafael"
      }
    },
    {
      "id": "51819a14",
      "sfl": 1.895,
      "quantity": 10,
      "itemId": 614,
      "collection": "collectibles",
      "source": "listing",
      "fulfilledAt": 1755758680726,
      "initiatedBy": {
        "id": 55890,
        "bumpkinUri": "0_v1_47_1_51_185_504_22_226_326_27_238_0_0_450_374_0_177",
        "username": "Yesim"
      },
      "fulfilledBy": {
        "id": 11,
        "bumpkinUri": "0_v1_306_90_52_62_234_89_226_475_29_514_86_0_276_72_0_266",
        "username": "rafael"
      }
    },
    {
      "id": "5d5df2f5",
      "sfl": 26.3897,
      "quantity": 100,
      "itemId": 641,
      "collection": "collectibles",
      "source": "listing",
      "fulfilledAt": 1755758534155,
      "initiatedBy": {
        "id": 48660,
        "bumpkinUri": "0_v1_71_1_63_0_0_22_226_81_0_0_0_0_267_73_0_266",
        "username": "Kerim"
      },
      "fulfilledBy": {
        "id": 11,
        "bumpkinUri": "0_v1_306_90_52_62_234_89_226_475_29_514_86_0_276_72_0_266",
        "username": "rafael"
      }
    },
    {
      "id": "64da0746",
      "sfl": 4.826,
      "quantity": 20,
      "itemId": 645,
      "collection": "collectibles",
      "source": "listing",
      "fulfilledAt": 1755742240306,
      "initiatedBy": {
        "id": 8716851572060369,
        "bumpkinUri": "0_v1_47_1_52_88_234_89_240_475_0_0_86_483_451",
        "username": "Muoi"
      },
      "fulfilledBy": {
        "id": 11,
        "bumpkinUri": "0_v1_306_90_52_62_234_89_226_475_29_514_86_0_276_72_0_266",
        "username": "rafael"
      }
    },
    {
      "id": "641809c0",
      "sfl": 5.0671,
      "quantity": 21,
      "itemId": 645,
      "collection": "collectibles",
      "source": "listing",
      "fulfilledAt": 1755742234159,
      "initiatedBy": {
        "id": 8716851572060369,
        "bumpkinUri": "0_v1_47_1_52_88_234_89_240_475_0_0_86_483_451",
        "username": "Muoi"
      },
      "fulfilledBy": {
        "id": 11,
        "bumpkinUri": "0_v1_306_90_52_62_234_89_226_475_29_514_86_0_276_72_0_266",
        "username": "rafael"
      }
    },
    {
      "id": "e23bc482",
      "sfl": 5.5495,
      "quantity": 23,
      "itemId": 645,
      "collection": "collectibles",
      "source": "listing",
      "fulfilledAt": 1755742230056,
      "initiatedBy": {
        "id": 142979,
        "bumpkinUri": "0_v1_83_90_184_503_504_0_414_505_30_0_86_0_0_374",
        "username": "DeltaOmega"
      },
      "fulfilledBy": {
        "id": 11,
        "bumpkinUri": "0_v1_306_90_52_62_234_89_226_475_29_514_86_0_276_72_0_266",
        "username": "rafael"
      }
    },
    {
      "id": "f89e1eef",
      "sfl": 10.3293,
      "quantity": 25,
      "itemId": 253,
      "collection": "collectibles",
      "source": "listing",
      "fulfilledAt": 1755567555843,
      "initiatedBy": {
        "id": 48660,
        "bumpkinUri": "0_v1_71_1_63_0_0_22_226_81_0_0_0_0_267_73_0_266",
        "username": "Kerim"
      },
      "fulfilledBy": {
        "id": 11,
        "bumpkinUri": "0_v1_306_90_52_62_234_89_226_475_29_514_86_0_276_72_0_266",
        "username": "rafael"
      }
    },
    {
      "id": "499308cb",
      "sfl": 61,
      "quantity": 100,
      "itemId": 254,
      "collection": "collectibles",
      "source": "listing",
      "fulfilledAt": 1755567539567,
      "initiatedBy": {
        "id": 5332901445491331,
        "bumpkinUri": "0_v1_0_90_52_342_46_34_23_395",
        "username": "LUIS77"
      },
      "fulfilledBy": {
        "id": 11,
        "bumpkinUri": "0_v1_306_90_52_62_234_89_226_475_29_514_86_0_276_72_0_266",
        "username": "rafael"
      }
    },
    {
      "id": "fc47c33d",
      "sfl": 8.6,
      "quantity": 25,
      "itemId": 252,
      "collection": "collectibles",
      "source": "listing",
      "fulfilledAt": 1755567485968,
      "initiatedBy": {
        "id": 133151,
        "bumpkinUri": "0_v1_364_263_50_335_338_34_226_395_501_238_0_427_0_0_0_177",
        "username": "MariiO"
      },
      "fulfilledBy": {
        "id": 11,
        "bumpkinUri": "0_v1_306_90_52_62_234_89_226_475_29_514_86_0_276_72_0_266",
        "username": "rafael"
      }
    },
    {
      "id": "669f289e",
      "sfl": 24.96,
      "quantity": 100,
      "itemId": 641,
      "collection": "collectibles",
      "source": "listing",
      "fulfilledAt": 1755566305945,
      "initiatedBy": {
        "id": 186602,
        "bumpkinUri": "0_v1_352_263_97_0_0_280_477_424_351_132_312_427_0_189_0_266",
        "username": "discount"
      },
      "fulfilledBy": {
        "id": 11,
        "bumpkinUri": "0_v1_306_90_52_62_234_89_226_475_29_514_86_0_276_72_0_266",
        "username": "rafael"
      }
    },
    {
      "id": "a4fc6b03",
      "sfl": 3,
      "quantity": 114,
      "itemId": 214,
      "collection": "collectibles",
      "source": "listing",
      "fulfilledAt": 1755493554788,
      "initiatedBy": {
        "id": 161928,
        "bumpkinUri": "0_v1_47_90_7_282_20_34_210_476_0_0_86_174_0_0_0_266",
        "username": "HolyKikyo"
      },
      "fulfilledBy": {
        "id": 11,
        "bumpkinUri": "0_v1_306_90_52_62_234_89_226_475_29_514_86_0_276_72_0_266",
        "username": "rafael"
      }
    },
    {
      "id": "1e1344bc",
      "sfl": 0.52,
      "quantity": 20,
      "itemId": 214,
      "collection": "collectibles",
      "source": "listing",
      "fulfilledAt": 1755493544627,
      "initiatedBy": {
        "id": 1750540559978793,
        "bumpkinUri": "0_v1_48_1_43_13_234_89_23_125_0_0_0_458",
        "username": "Panda18"
      },
      "fulfilledBy": {
        "id": 11,
        "bumpkinUri": "0_v1_306_90_52_62_234_89_226_475_29_514_86_0_276_72_0_266",
        "username": "rafael"
      }
    },
    {
      "id": "b462678f",
      "sfl": 0.52,
      "quantity": 20,
      "itemId": 214,
      "collection": "collectibles",
      "source": "listing",
      "fulfilledAt": 1755493540491,
      "initiatedBy": {
        "id": 1750540559978793,
        "bumpkinUri": "0_v1_48_1_43_13_234_89_23_125_0_0_0_458",
        "username": "Panda18"
      },
      "fulfilledBy": {
        "id": 11,
        "bumpkinUri": "0_v1_306_90_52_62_234_89_226_475_29_514_86_0_276_72_0_266",
        "username": "rafael"
      }
    },
    {
      "id": "a054c961",
      "sfl": 0.921,
      "quantity": 36,
      "itemId": 605,
      "collection": "collectibles",
      "source": "offer",
      "fulfilledAt": 1755486421407,
      "initiatedBy": {
        "id": 7550464461994316,
        "bumpkinUri": "0_v1_306_90_52_62_234_89_226_475_29_514_86_0_276_72_0_266",
        "username": "rafael"
      },
      "fulfilledBy": {
        "id": 11,
        "bumpkinUri": "0_v1_48_90_5_0_504_89_226_505_0_238_86_401",
        "username": "Ramsessnk"
      }
    },
    {
      "id": "5a48e473",
      "sfl": 1.535,
      "quantity": 60,
      "itemId": 605,
      "collection": "collectibles",
      "source": "offer",
      "fulfilledAt": 1755486401787,
      "initiatedBy": {
        "id": 3014462413125171,
        "bumpkinUri": "0_v1_306_90_52_62_234_89_226_475_29_514_86_0_276_72_0_266",
        "username": "rafael"
      },
      "fulfilledBy": {
        "id": 11,
        "bumpkinUri": "0_v1_47_1_51_13_18_89_23_395",
        "username": "xunil"
      }
    },
    {
      "id": "cb542ff7",
      "sfl": 1.024,
      "quantity": 40,
      "itemId": 605,
      "collection": "collectibles",
      "source": "offer",
      "fulfilledAt": 1755486392255,
      "initiatedBy": {
        "id": 2652671856823967,
        "bumpkinUri": "0_v1_306_90_52_62_234_89_226_475_29_514_86_0_276_72_0_266",
        "username": "rafael"
      },
      "fulfilledBy": {
        "id": 11,
        "bumpkinUri": "0_v1_47_3_43_13_35_34_23",
        "username": "OumOumOum"
      }
    },
    {
      "id": "d9e36ce2",
      "sfl": 3.9706,
      "quantity": 20,
      "itemId": 614,
      "collection": "collectibles",
      "source": "listing",
      "fulfilledAt": 1755486338555,
      "initiatedBy": {
        "id": 163902,
        "bumpkinUri": "0_v1_48_1_43_88_234_34_240_395_0_0_0_0_451",
        "username": "liacarames"
      },
      "fulfilledBy": {
        "id": 11,
        "bumpkinUri": "0_v1_306_90_52_62_234_89_226_475_29_514_86_0_276_72_0_266",
        "username": "rafael"
      }
    },
    {
      "id": "fdd577d0",
      "sfl": 11.6997,
      "quantity": 12,
      "itemId": 636,
      "collection": "collectibles",
      "source": "listing",
      "fulfilledAt": 1755486282599,
      "initiatedBy": {
        "id": 5188546816939488,
        "bumpkinUri": "0_v1_32_90_184_459_234_89_240_476_0_228_86_458_451_0_0_177",
        "username": "lollipoppp"
      },
      "fulfilledBy": {
        "id": 11,
        "bumpkinUri": "0_v1_306_90_52_62_234_89_226_475_29_514_86_0_276_72_0_266",
        "username": "rafael"
      }
    },
    {
      "id": "96edeb36",
      "sfl": 7.39,
      "quantity": 1,
      "itemId": 240,
      "collection": "collectibles",
      "source": "listing",
      "fulfilledAt": 1755481893210,
      "initiatedBy": {
        "id": 169246,
        "bumpkinUri": "0_v1_48_3_42_15_234_89_240_462_0_228_0_0_450",
        "username": "Freakazoid"
      },
      "fulfilledBy": {
        "id": 11,
        "bumpkinUri": "0_v1_306_90_52_62_234_89_226_475_29_514_86_0_276_72_0_266",
        "username": "rafael"
      }
    },
    {
      "id": "3056d40f",
      "sfl": 2.375,
      "quantity": 5,
      "itemId": 267,
      "collection": "collectibles",
      "source": "listing",
      "fulfilledAt": 1755442199435,
      "initiatedBy": {
        "id": 2137961789576788,
        "bumpkinUri": "0_v1_47_3_5_185_18_41_23_395_0_0_0_458_451",
        "username": "diguinho"
      },
      "fulfilledBy": {
        "id": 11,
        "bumpkinUri": "0_v1_306_90_52_62_234_89_226_475_29_514_86_0_276_72_0_266",
        "username": "rafael"
      }
    },
    {
      "id": "3f1fa634",
      "sfl": 1.9478,
      "quantity": 2,
      "itemId": 266,
      "collection": "collectibles",
      "source": "listing",
      "fulfilledAt": 1755442183051,
      "initiatedBy": {
        "id": 6967337550236960,
        "bumpkinUri": "0_v1_48_1_5_13_234_34_240_0_0_228_0_0_451",
        "username": "JISUSGUST184"
      },
      "fulfilledBy": {
        "id": 11,
        "bumpkinUri": "0_v1_306_90_52_62_234_89_226_475_29_514_86_0_276_72_0_266",
        "username": "rafael"
      }
    },
    {
      "id": "71d415cd",
      "sfl": 1.9289,
      "quantity": 10,
      "itemId": 268,
      "collection": "collectibles",
      "source": "listing",
      "fulfilledAt": 1755442134781,
      "initiatedBy": {
        "id": 144839,
        "bumpkinUri": "0_v1_48_2_51_342_46_22_23_395_0_0_0_0_451_0_0_266",
        "username": "dikaa"
      },
      "fulfilledBy": {
        "id": 11,
        "bumpkinUri": "0_v1_306_90_52_62_234_89_226_475_29_514_86_0_276_72_0_266",
        "username": "rafael"
      }
    },
    {
      "id": "18d7ce5a",
      "sfl": 11.1,
      "quantity": 500,
      "itemId": 605,
      "collection": "collectibles",
      "source": "offer",
      "fulfilledAt": 1755442094405,
      "initiatedBy": {
        "id": 8266678176302855,
        "bumpkinUri": "0_v1_306_90_52_62_234_89_226_475_29_514_86_0_276_72_0_266",
        "username": "rafael"
      },
      "fulfilledBy": {
        "id": 11,
        "bumpkinUri": "0_v1_32_90_202_282_234_89_477_424_501_228_408_350_0_374_0_177",
        "username": "DODGE"
      }
    },
    {
      "id": "8607c900",
      "sfl": 11.1011,
      "quantity": 500,
      "itemId": 605,
      "collection": "collectibles",
      "source": "offer",
      "fulfilledAt": 1755442083547,
      "initiatedBy": {
        "id": 73394,
        "bumpkinUri": "0_v1_306_90_52_62_234_89_226_475_29_514_86_0_276_72_0_266",
        "username": "rafael"
      },
      "fulfilledBy": {
        "id": 11,
        "bumpkinUri": "0_v1_352_90_202_474_234_41_257_424_29_228_86_401_276_374_0_266",
        "username": "ISAAC"
      }
    },
    {
      "id": "f82a1c76",
      "sfl": 24.949,
      "quantity": 100,
      "itemId": 641,
      "collection": "collectibles",
      "source": "listing",
      "fulfilledAt": 1755431703161,
      "initiatedBy": {
        "id": 28893,
        "bumpkinUri": "0_v1_364_90_97_282_504_22_400_255_0_381_408_0_451_374_0_177",
        "username": "andrelop2001"
      },
      "fulfilledBy": {
        "id": 11,
        "bumpkinUri": "0_v1_306_90_52_62_234_89_226_475_29_514_86_0_276_72_0_266",
        "username": "rafael"
      }
    },
    {
      "id": "3ee2e363",
      "sfl": 4.05,
      "quantity": 100,
      "itemId": 211,
      "collection": "collectibles",
      "source": "listing",
      "fulfilledAt": 1755396640704,
      "initiatedBy": {
        "id": 7960891880012494,
        "bumpkinUri": "0_v1_47_3_52_13_234_22_240_395_0_230_0_401_453",
        "username": "Sharkoon"
      },
      "fulfilledBy": {
        "id": 11,
        "bumpkinUri": "0_v1_306_90_52_62_234_89_226_475_29_514_86_0_276_72_0_266",
        "username": "rafael"
      }
    },
    {
      "id": "612c28a9",
      "sfl": 14.3173,
      "quantity": 100,
      "itemId": 641,
      "collection": "collectibles",
      "source": "listing",
      "fulfilledAt": 1754992556841,
      "initiatedBy": {
        "id": 171104,
        "bumpkinUri": "0_v1_348_2_184_282_18_22_400_476_501_383_86_0_0_189_0_266",
        "username": "Snoo"
      },
      "fulfilledBy": {
        "id": 11,
        "bumpkinUri": "0_v1_306_90_52_62_234_89_226_475_29_514_86_0_276_72_0_266",
        "username": "rafael"
      }
    },
    {
      "id": "ac506803",
      "sfl": 2.2907,
      "quantity": 16,
      "itemId": 641,
      "collection": "collectibles",
      "source": "listing",
      "fulfilledAt": 1754992479087,
      "initiatedBy": {
        "id": 2892943171130687,
        "bumpkinUri": "0_v1_47_1_50_88_19_89_45_253",
        "username": "Iffi"
      },
      "fulfilledBy": {
        "id": 11,
        "bumpkinUri": "0_v1_306_90_52_62_234_89_226_475_29_514_86_0_276_72_0_266",
        "username": "rafael"
      }
    },
    {
      "id": "508c4f2d",
      "sfl": 0.1948,
      "quantity": 10,
      "itemId": 265,
      "collection": "collectibles",
      "source": "listing",
      "fulfilledAt": 1746460904571,
      "initiatedBy": {
        "id": 7489472711567773,
        "bumpkinUri": "0_v1_32_90_5_181_504_89_240_395_29_0_86_0_452_374",
        "username": "GOODFarmer11"
      },
      "fulfilledBy": {
        "id": 11,
        "bumpkinUri": "0_v1_306_90_52_62_234_89_226_475_29_514_86_0_276_72_0_266",
        "username": "rafael"
      }
    },
    {
      "id": "45b24dad",
      "sfl": 0.9739,
      "quantity": 50,
      "itemId": 265,
      "collection": "collectibles",
      "source": "listing",
      "fulfilledAt": 1746460874723,
      "initiatedBy": {
        "id": 7480438069467076,
        "bumpkinUri": "0_v1_32_4_5_317_504_89_226_505_0_228_86_483_451_374",
        "username": "er4smus"
      },
      "fulfilledBy": {
        "id": 11,
        "bumpkinUri": "0_v1_306_90_52_62_234_89_226_475_29_514_86_0_276_72_0_266",
        "username": "rafael"
      }
    },
    {
      "id": "0748f189",
      "sfl": 0.857,
      "quantity": 44,
      "itemId": 265,
      "collection": "collectibles",
      "source": "listing",
      "fulfilledAt": 1746460864722,
      "initiatedBy": {
        "id": 1652318601454319,
        "bumpkinUri": "0_v1_48_1_7_13_20_22_45",
        "username": "luzz"
      },
      "fulfilledBy": {
        "id": 11,
        "bumpkinUri": "0_v1_306_90_52_62_234_89_226_475_29_514_86_0_276_72_0_266",
        "username": "rafael"
      }
    },
    {
      "id": "a7485a71",
      "sfl": 0.314,
      "quantity": 1,
      "itemId": 1509,
      "collection": "collectibles",
      "source": "listing",
      "fulfilledAt": 1746408252858,
      "initiatedBy": {
        "id": 2614282631960071,
        "bumpkinUri": "0_v1_32_90_5_13_18_22_226_255",
        "username": "Peq"
      },
      "fulfilledBy": {
        "id": 11,
        "bumpkinUri": "0_v1_306_90_52_62_234_89_226_475_29_514_86_0_276_72_0_266",
        "username": "rafael"
      }
    },
    {
      "id": "0000086727#2pPj2YpGjccy1PqHmdCwf6Ocuqd",
      "sfl": 6.3311,
      "quantity": 73,
      "itemId": 212,
      "collection": "collectibles",
      "source": "listing",
      "fulfilledAt": 1732674811192,
      "initiatedBy": {
        "id": 1447,
        "bumpkinUri": "0_v1_364_3_7_342_18_41_44_396_351_0_0_117",
        "username": "NoBody"
      },
      "fulfilledBy": {
        "id": 11,
        "bumpkinUri": "0_v1_306_90_52_62_234_89_226_475_29_514_86_0_276_72_0_266",
        "username": "rafael"
      }
    }
  ]
}