{
  "username": "droid",
  "overview": {
    "balance": 1.69,
    "coins": 164515.0,
    "gems": 0.0,
    "earned_sfl": 8180.79,
    "earned_coins": 164515.0,
    "spent_sfl": 12297.69,
    "items_sold": 7614.0,
    "trade_points": 11367.53,
    "last_updated": "2026-01-31 05:14 PM",
    "active_listings": 5
  },
  "buys": [
    {
      "date": "2026-01-31",
      "time": "04:11 PM",
      "type": "BUY",
      "item": "Tomato",
      "quantity": 100,
      "price_text": "0.4901 SFL",
      "price": 0.4901,
      "counterparty": "dungdz01",
      "farm_id": "-",
      "trade_id": "8cd7a25b"
    },
    {
      "date": "2026-01-31",
      "time": "04:10 PM",
      "type": "BUY",
      "item": "Stone",
      "quantity": 30,
      "price_text": "0.4735 SFL",
      "price": 0.4735,
      "counterparty": "jessan",
      "farm_id": "-",
      "trade_id": "5e231479"
    },
    {
      "date": "2026-01-31",
      "time": "03:26 PM",
      "type": "BUY",
      "item": "Milk",
      "quantity": 30,
      "price_text": "3.762 SFL",
      "price": 3.762,
      "counterparty": "MariiO",
      "farm_id": "-",
      "trade_id": "8ea8e8a2"
    },
    {
      "date": "2026-01-31",
      "time": "03:26 PM",
      "type": "BUY",
      "item": "Honey",
      "quantity": 18,
      "price_text": "1.0439 SFL",
      "price": 1.0439,
      "counterparty": "Lord",
      "farm_id": "-",
      "trade_id": "65b10878"
    },
    {
      "date": "2026-01-31",
      "time": "03:25 PM",
      "type": "BUY",
      "item": "Tomato",
      "quantity": 50,
      "price_text": "0.2453 SFL",
      "price": 0.2453,
      "counterparty": "dungdz01",
      "farm_id": "-",
      "trade_id": "a0089ebe"
    },
    {
      "date": "2026-01-31",
      "time": "02:49 PM",
      "type": "BUY",
      "item": "Milk",
      "quantity": 25,
      "price_text": "3.12 SFL",
      "price": 3.12,
      "counterparty": "DDoubleD",
      "farm_id": "-",
      "trade_id": "c979b462"
    },
    {
      "date": "2026-01-31",
      "time": "11:08 AM",
      "type": "BUY",
      "item": "Stone",
      "quantity": 43,
      "price_text": "0.6837 SFL",
      "price": 0.6837,
      "counterparty": "thecatTHz",
      "farm_id": "-",
      "trade_id": "729e9c15"
    },
    {
      "date": "2026-01-31",
      "time": "10:29 AM",
      "type": "BUY",
      "item": "Honey",
      "quantity": 10,
      "price_text": "0.6383 SFL",
      "price": 0.6383,
      "counterparty": "kingkafa",
      "farm_id": "-",
      "trade_id": "7058188f"
    },
    {
      "date": "2026-01-31",
      "time": "08:55 AM",
      "type": "BUY",
      "item": "Milk",
      "quantity": 45,
      "price_text": "5.5113 SFL",
      "price": 5.5113,
      "counterparty": "Theniaky",
      "farm_id": "-",
      "trade_id": "7828068f"
    },
    {
      "date": "2026-01-31",
      "time": "08:26 AM",
      "type": "BUY",
      "item": "Parsnip",
      "quantity": 50,
      "price_text": "0.9999 SFL",
      "price": 0.9999,
      "counterparty": "MaykWazalski",
      "farm_id": "-",
      "trade_id": "ce624f11"
    },
    {
      "date": "2026-01-31",
      "time": "08:25 AM",
      "type": "BUY",
      "item": "Beetroot",
      "quantity": 100,
      "price_text": "0.6799 SFL",
      "price": 0.6799,
      "counterparty": "lliw",
      "farm_id": "-",
      "trade_id": "6b60fa1a"
    },
    {
      "date": "2026-01-31",
      "time": "05:56 AM",
      "type": "BUY",
      "item": "Honey",
      "quantity": 23,
      "price_text": "1.3294 SFL",
      "price": 1.3294,
      "counterparty": "Kajidaori",
      "farm_id": "-",
      "trade_id": "adc13db2"
    },
    {
      "date": "2026-01-31",
      "time": "05:21 AM",
      "type": "BUY",
      "item": "Milk",
      "quantity": 100,
      "price_text": "12.2999 SFL",
      "price": 12.2999,
      "counterparty": "OxCh1n1",
      "farm_id": "-",
      "trade_id": "c9fe4023"
    },
    {
      "date": "2026-01-31",
      "time": "05:20 AM",
      "type": "BUY",
      "item": "Milk",
      "quantity": 13,
      "price_text": "1.5989 SFL",
      "price": 1.5989,
      "counterparty": "yambra",
      "farm_id": "-",
      "trade_id": "3681ef47"
    },
    {
      "date": "2026-01-31",
      "time": "05:20 AM",
      "type": "BUY",
      "item": "Milk",
      "quantity": 13,
      "price_text": "1.5989 SFL",
      "price": 1.5989,
      "counterparty": "DoughFruit",
      "farm_id": "-",
      "trade_id": "bf43cce4"
    },
    {
      "date": "2026-01-31",
      "time": "05:20 AM",
      "type": "BUY",
      "item": "Milk",
      "quantity": 10,
      "price_text": "1.2299 SFL",
      "price": 1.2299,
      "counterparty": "MKaKaRoTo",
      "farm_id": "-",
      "trade_id": "d271feea"
    },
    {
      "date": "2026-01-31",
      "time": "03:53 AM",
      "type": "BUY",
      "item": "Wool",
      "quantity": 19,
      "price_text": "1.124 SFL",
      "price": 1.124,
      "counterparty": "Gps3d",
      "farm_id": "-",
      "trade_id": "b91079ac"
    },
    {
      "date": "2026-01-31",
      "time": "03:47 AM",
      "type": "BUY",
      "item": "Leather",
      "quantity": 50,
      "price_text": "6.175 SFL",
      "price": 6.175,
      "counterparty": "Alcharyx",
      "farm_id": "-",
      "trade_id": "b71060bb"
    },
    {
      "date": "2026-01-31",
      "time": "03:42 AM",
      "type": "BUY",
      "item": "Milk",
      "quantity": 9,
      "price_text": "1.1115 SFL",
      "price": 1.1115,
      "counterparty": "Locoskill",
      "farm_id": "-",
      "trade_id": "6463026d"
    },
    {
      "date": "2026-01-31",
      "time": "03:42 AM",
      "type": "BUY",
      "item": "Milk",
      "quantity": 17,
      "price_text": "2.0995 SFL",
      "price": 2.0995,
      "counterparty": "YanX",
      "farm_id": "-",
      "trade_id": "3f62e616"
    },
    {
      "date": "2026-01-31",
      "time": "03:37 AM",
      "type": "BUY",
      "item": "Artichoke",
      "quantity": 28,
      "price_text": "0.2736 SFL",
      "price": 0.2736,
      "counterparty": "MUSASIDHU",
      "farm_id": "-",
      "trade_id": "33d463b1"
    },
    {
      "date": "2026-01-31",
      "time": "03:36 AM",
      "type": "BUY",
      "item": "Milk",
      "quantity": 10,
      "price_text": "1.299 SFL",
      "price": 1.299,
      "counterparty": "Niteshockers",
      "farm_id": "-",
      "trade_id": "5d4e4ffb"
    },
    {
      "date": "2026-01-31",
      "time": "03:36 AM",
      "type": "BUY",
      "item": "Milk",
      "quantity": 10,
      "price_text": "1.29 SFL",
      "price": 1.29,
      "counterparty": "Ratatouille",
      "farm_id": "-",
      "trade_id": "3e2b950c"
    },
    {
      "date": "2026-01-30",
      "time": "06:05 PM",
      "type": "BUY",
      "item": "Stone",
      "quantity": 50,
      "price_text": "0.78 SFL",
      "price": 0.78,
      "counterparty": "JohanVash",
      "farm_id": "-",
      "trade_id": "59d9344b"
    },
    {
      "date": "2026-01-30",
      "time": "05:05 PM",
      "type": "BUY",
      "item": "Lemon",
      "quantity": 100,
      "price_text": "0.9903 SFL",
      "price": 0.9903,
      "counterparty": "Noriega",
      "farm_id": "-",
      "trade_id": "5005f9fa"
    },
    {
      "date": "2026-01-30",
      "time": "05:04 PM",
      "type": "BUY",
      "item": "Lemon",
      "quantity": 25,
      "price_text": "0.2478 SFL",
      "price": 0.2478,
      "counterparty": "Nirtuguela",
      "farm_id": "-",
      "trade_id": "0ac70a48"
    },
    {
      "date": "2026-01-30",
      "time": "05:04 PM",
      "type": "BUY",
      "item": "Egg",
      "quantity": 30,
      "price_text": "0.6626 SFL",
      "price": 0.6626,
      "counterparty": "Vikingo2050",
      "farm_id": "-",
      "trade_id": "4b67560b"
    },
    {
      "date": "2026-01-30",
      "time": "03:13 PM",
      "type": "BUY",
      "item": "Milk",
      "quantity": 9,
      "price_text": "1.0928 SFL",
      "price": 1.0928,
      "counterparty": "supremus",
      "farm_id": "-",
      "trade_id": "73c4ab77"
    },
    {
      "date": "2026-01-30",
      "time": "03:12 PM",
      "type": "BUY",
      "item": "Honey",
      "quantity": 7,
      "price_text": "0.4249 SFL",
      "price": 0.4249,
      "counterparty": "Ehd",
      "farm_id": "-",
      "trade_id": "9af877e4"
    },
    {
      "date": "2026-01-30",
      "time": "01:33 PM",
      "type": "BUY",
      "item": "Milk",
      "quantity": 12,
      "price_text": "1.4646 SFL",
      "price": 1.4646,
      "counterparty": "BlackwolfNS",
      "farm_id": "-",
      "trade_id": "433e4b78"
    },
    {
      "date": "2026-01-30",
      "time": "01:33 PM",
      "type": "BUY",
      "item": "Milk",
      "quantity": 17,
      "price_text": "2.0706 SFL",
      "price": 2.0706,
      "counterparty": "Hooa",
      "farm_id": "-",
      "trade_id": "def8ed77"
    },
    {
      "date": "2026-01-30",
      "time": "01:33 PM",
      "type": "BUY",
      "item": "Tomato",
      "quantity": 200,
      "price_text": "0.978 SFL",
      "price": 0.978,
      "counterparty": "ShimKoy",
      "farm_id": "-",
      "trade_id": "3a02778a"
    },
    {
      "date": "2026-01-30",
      "time": "12:55 PM",
      "type": "BUY",
      "item": "Leather",
      "quantity": 5,
      "price_text": "0.6 SFL",
      "price": 0.6,
      "counterparty": "Shivin",
      "farm_id": "-",
      "trade_id": "ef5857bb"
    },
    {
      "date": "2026-01-30",
      "time": "12:31 PM",
      "type": "BUY",
      "item": "Milk",
      "quantity": 38,
      "price_text": "4.56 SFL",
      "price": 4.56,
      "counterparty": "Veayce",
      "farm_id": "-",
      "trade_id": "88572b0b"
    },
    {
      "date": "2026-01-30",
      "time": "06:30 AM",
      "type": "BUY",
      "item": "Stone",
      "quantity": 200,
      "price_text": "3.2 SFL",
      "price": 3.2,
      "counterparty": "Sovereign",
      "farm_id": "-",
      "trade_id": "d0264092"
    },
    {
      "date": "2026-01-30",
      "time": "04:55 AM",
      "type": "BUY",
      "item": "Yellow Daffodil",
      "quantity": 1,
      "price_text": "0.5979 SFL",
      "price": 0.5979,
      "counterparty": "Matahari",
      "farm_id": "-",
      "trade_id": "2577b0df"
    },
    {
      "date": "2026-01-30",
      "time": "04:54 AM",
      "type": "BUY",
      "item": "Yellow Balloon",
      "quantity": 1,
      "price_text": "0.89 SFL",
      "price": 0.89,
      "counterparty": "Jessicax3",
      "farm_id": "-",
      "trade_id": "ebacc241"
    },
    {
      "date": "2026-01-30",
      "time": "04:54 AM",
      "type": "BUY",
      "item": "Honey",
      "quantity": 5,
      "price_text": "0.3175 SFL",
      "price": 0.3175,
      "counterparty": "Persephone",
      "farm_id": "-",
      "trade_id": "2ddc0778"
    },
    {
      "date": "2026-01-30",
      "time": "04:53 AM",
      "type": "BUY",
      "item": "Artichoke",
      "quantity": 20,
      "price_text": "0.1946 SFL",
      "price": 0.1946,
      "counterparty": "JR2025JR",
      "farm_id": "-",
      "trade_id": "31d76810"
    },
    {
      "date": "2026-01-30",
      "time": "04:52 AM",
      "type": "BUY",
      "item": "Artichoke",
      "quantity": 50,
      "price_text": "0.4864 SFL",
      "price": 0.4864,
      "counterparty": "Flaa",
      "farm_id": "-",
      "trade_id": "1d17a312"
    },
    {
      "date": "2026-01-30",
      "time": "04:51 AM",
      "type": "BUY",
      "item": "Carrot",
      "quantity": 500,
      "price_text": "0.8716 SFL",
      "price": 0.8716,
      "counterparty": "Legaty",
      "farm_id": "-",
      "trade_id": "2ea95ae4"
    },
    {
      "date": "2026-01-30",
      "time": "01:53 AM",
      "type": "BUY",
      "item": "Wool",
      "quantity": 10,
      "price_text": "0.506 SFL",
      "price": 0.506,
      "counterparty": "Digits",
      "farm_id": "-",
      "trade_id": "192a20b8"
    },
    {
      "date": "2026-01-30",
      "time": "01:42 AM",
      "type": "BUY",
      "item": "Honey",
      "quantity": 10,
      "price_text": "0.6352 SFL",
      "price": 0.6352,
      "counterparty": "Pepes",
      "farm_id": "-",
      "trade_id": "2576f0c3"
    },
    {
      "date": "2026-01-30",
      "time": "01:19 AM",
      "type": "BUY",
      "item": "Parsnip",
      "quantity": 100,
      "price_text": "1.76 SFL",
      "price": 1.76,
      "counterparty": "PhuongGL81",
      "farm_id": "-",
      "trade_id": "581fbbb7"
    },
    {
      "date": "2026-01-30",
      "time": "01:17 AM",
      "type": "BUY",
      "item": "Cauliflower",
      "quantity": 100,
      "price_text": "1.1619 SFL",
      "price": 1.1619,
      "counterparty": "Kitetsu",
      "farm_id": "-",
      "trade_id": "f144793d"
    },
    {
      "date": "2026-01-30",
      "time": "01:16 AM",
      "type": "BUY",
      "item": "Wood",
      "quantity": 50,
      "price_text": "0.4549 SFL",
      "price": 0.4549,
      "counterparty": "Goneribs",
      "farm_id": "-",
      "trade_id": "7af8ffb4"
    },
    {
      "date": "2026-01-30",
      "time": "01:10 AM",
      "type": "BUY",
      "item": "Lemon",
      "quantity": 10,
      "price_text": "0.099 SFL",
      "price": 0.099,
      "counterparty": "Vrelorein",
      "farm_id": "-",
      "trade_id": "69e2507f"
    },
    {
      "date": "2026-01-30",
      "time": "01:10 AM",
      "type": "BUY",
      "item": "Lemon",
      "quantity": 10,
      "price_text": "0.099 SFL",
      "price": 0.099,
      "counterparty": "Vrelorein",
      "farm_id": "-",
      "trade_id": "ae4bee89"
    },
    {
      "date": "2026-01-30",
      "time": "01:10 AM",
      "type": "BUY",
      "item": "Lemon",
      "quantity": 10,
      "price_text": "0.099 SFL",
      "price": 0.099,
      "counterparty": "Vrelorein",
      "farm_id": "-",
      "trade_id": "bcf85d56"
    },
    {
      "date": "2026-01-30",
      "time": "01:09 AM",
      "type": "BUY",
      "item": "Leather",
      "quantity": 30,
      "price_text": "3.5653 SFL",
      "price": 3.5653,
      "counterparty": "Lekowem",
      "farm_id": "-",
      "trade_id": "f72d0ae5"
    },
    {
      "date": "2026-01-30",
      "time": "01:08 AM",
      "type": "BUY",
      "item": "Stone",
      "quantity": 48,
      "price_text": "0.769 SFL",
      "price": 0.769,
      "counterparty": "Adrian82",
      "farm_id": "-",
      "trade_id": "52b023ba"
    },
    {
      "date": "2026-01-29",
      "time": "05:20 PM",
      "type": "BUY",
      "item": "Yam",
      "quantity": 150,
      "price_text": "0.435 SFL",
      "price": 0.435,
      "counterparty": "TatyanaBZ",
      "farm_id": "-",
      "trade_id": "1b235460"
    },
    {
      "date": "2026-01-29",
      "time": "05:20 PM",
      "type": "BUY",
      "item": "Stone",
      "quantity": 25,
      "price_text": "0.3987 SFL",
      "price": 0.3987,
      "counterparty": "American19",
      "farm_id": "-",
      "trade_id": "b8e9582c"
    },
    {
      "date": "2026-01-29",
      "time": "05:20 PM",
      "type": "BUY",
      "item": "Stone",
      "quantity": 25,
      "price_text": "0.3987 SFL",
      "price": 0.3987,
      "counterparty": "American19",
      "farm_id": "-",
      "trade_id": "3e7a0354"
    },
    {
      "date": "2026-01-29",
      "time": "05:19 PM",
      "type": "BUY",
      "item": "Stone",
      "quantity": 25,
      "price_text": "0.3987 SFL",
      "price": 0.3987,
      "counterparty": "American19",
      "farm_id": "-",
      "trade_id": "2286ba03"
    },
    {
      "date": "2026-01-29",
      "time": "05:19 PM",
      "type": "BUY",
      "item": "Wool",
      "quantity": 10,
      "price_text": "0.5833 SFL",
      "price": 0.5833,
      "counterparty": "wuack",
      "farm_id": "-",
      "trade_id": "68a5c7bf"
    },
    {
      "date": "2026-01-29",
      "time": "05:18 PM",
      "type": "BUY",
      "item": "Leather",
      "quantity": 10,
      "price_text": "1.1879 SFL",
      "price": 1.1879,
      "counterparty": "Teka",
      "farm_id": "-",
      "trade_id": "f66c71d8"
    },
    {
      "date": "2026-01-29",
      "time": "03:05 PM",
      "type": "BUY",
      "item": "Carrot",
      "quantity": 100,
      "price_text": "0.1843 SFL",
      "price": 0.1843,
      "counterparty": "ciki79",
      "farm_id": "-",
      "trade_id": "1790bf82"
    },
    {
      "date": "2026-01-29",
      "time": "03:03 PM",
      "type": "BUY",
      "item": "Stone",
      "quantity": 25,
      "price_text": "0.3999 SFL",
      "price": 0.3999,
      "counterparty": "Lorikvill",
      "farm_id": "-",
      "trade_id": "b074363c"
    },
    {
      "date": "2026-01-29",
      "time": "03:02 PM",
      "type": "BUY",
      "item": "Stone",
      "quantity": 25,
      "price_text": "0.3999 SFL",
      "price": 0.3999,
      "counterparty": "Lorikvill",
      "farm_id": "-",
      "trade_id": "91e872a9"
    },
    {
      "date": "2026-01-29",
      "time": "02:21 PM",
      "type": "BUY",
      "item": "Artichoke",
      "quantity": 10,
      "price_text": "0.0962 SFL",
      "price": 0.0962,
      "counterparty": "Tapash",
      "farm_id": "-",
      "trade_id": "30a83411"
    },
    {
      "date": "2026-01-29",
      "time": "02:21 PM",
      "type": "BUY",
      "item": "Artichoke",
      "quantity": 18,
      "price_text": "0.1732 SFL",
      "price": 0.1732,
      "counterparty": "Tapash",
      "farm_id": "-",
      "trade_id": "d42e9b37"
    },
    {
      "date": "2026-01-29",
      "time": "02:21 PM",
      "type": "BUY",
      "item": "Artichoke",
      "quantity": 125,
      "price_text": "1.2025 SFL",
      "price": 1.2025,
      "counterparty": "Brahim",
      "farm_id": "-",
      "trade_id": "7c700ce7"
    },
    {
      "date": "2026-01-29",
      "time": "02:13 PM",
      "type": "BUY",
      "item": "Stone",
      "quantity": 100,
      "price_text": "1.59 SFL",
      "price": 1.59,
      "counterparty": "mapa1",
      "farm_id": "-",
      "trade_id": "e5b3551b"
    },
    {
      "date": "2026-01-29",
      "time": "02:08 PM",
      "type": "BUY",
      "item": "Leather",
      "quantity": 10,
      "price_text": "1.243 SFL",
      "price": 1.243,
      "counterparty": "Ein4n",
      "farm_id": "-",
      "trade_id": "77965f79"
    },
    {
      "date": "2026-01-29",
      "time": "02:07 PM",
      "type": "BUY",
      "item": "Honey",
      "quantity": 5,
      "price_text": "0.3175 SFL",
      "price": 0.3175,
      "counterparty": "PASILYOO",
      "farm_id": "-",
      "trade_id": "e714f763"
    },
    {
      "date": "2026-01-29",
      "time": "12:40 PM",
      "type": "BUY",
      "item": "Milk",
      "quantity": 10,
      "price_text": "1.3 SFL",
      "price": 1.3,
      "counterparty": "Kuky1",
      "farm_id": "-",
      "trade_id": "c0b2c611"
    },
    {
      "date": "2026-01-29",
      "time": "12:40 PM",
      "type": "BUY",
      "item": "Milk",
      "quantity": 10,
      "price_text": "1.3 SFL",
      "price": 1.3,
      "counterparty": "Kuky1",
      "farm_id": "-",
      "trade_id": "2aee8270"
    },
    {
      "date": "2026-01-29",
      "time": "12:40 PM",
      "type": "BUY",
      "item": "Milk",
      "quantity": 10,
      "price_text": "1.3 SFL",
      "price": 1.3,
      "counterparty": "Kuky1",
      "farm_id": "-",
      "trade_id": "65cf1d15"
    },
    {
      "date": "2026-01-29",
      "time": "11:06 AM",
      "type": "BUY",
      "item": "Lemon",
      "quantity": 20,
      "price_text": "0.1988 SFL",
      "price": 0.1988,
      "counterparty": "Tato1",
      "farm_id": "-",
      "trade_id": "2f4bcbfc"
    },
    {
      "date": "2026-01-29",
      "time": "09:13 AM",
      "type": "BUY",
      "item": "Leather",
      "quantity": 9,
      "price_text": "1.08 SFL",
      "price": 1.08,
      "counterparty": "SOLDERET",
      "farm_id": "-",
      "trade_id": "5b80756f"
    },
    {
      "date": "2026-01-29",
      "time": "09:13 AM",
      "type": "BUY",
      "item": "Honey",
      "quantity": 10,
      "price_text": "0.615 SFL",
      "price": 0.615,
      "counterparty": "Zanib",
      "farm_id": "-",
      "trade_id": "5fed7fff"
    },
    {
      "date": "2026-01-29",
      "time": "06:27 AM",
      "type": "BUY",
      "item": "Milk",
      "quantity": 12,
      "price_text": "1.4264 SFL",
      "price": 1.4264,
      "counterparty": "mephisto",
      "farm_id": "-",
      "trade_id": "f36155ba"
    },
    {
      "date": "2026-01-29",
      "time": "06:27 AM",
      "type": "BUY",
      "item": "Milk",
      "quantity": 23,
      "price_text": "2.7341 SFL",
      "price": 2.7341,
      "counterparty": "joyandit20",
      "farm_id": "-",
      "trade_id": "41b491ce"
    },
    {
      "date": "2026-01-29",
      "time": "06:22 AM",
      "type": "BUY",
      "item": "Crimstone",
      "quantity": 1,
      "price_text": "0.5313 SFL",
      "price": 0.5313,
      "counterparty": "Dragonsx",
      "farm_id": "-",
      "trade_id": "298fc037"
    },
    {
      "date": "2026-01-29",
      "time": "06:22 AM",
      "type": "BUY",
      "item": "Crimstone",
      "quantity": 3,
      "price_text": "1.593 SFL",
      "price": 1.593,
      "counterparty": "Tapiokka",
      "farm_id": "-",
      "trade_id": "6e706147"
    },
    {
      "date": "2026-01-29",
      "time": "06:22 AM",
      "type": "BUY",
      "item": "Crimstone",
      "quantity": 7,
      "price_text": "3.717 SFL",
      "price": 3.717,
      "counterparty": "Bighouse",
      "farm_id": "-",
      "trade_id": "60e4dae6"
    },
    {
      "date": "2026-01-29",
      "time": "06:08 AM",
      "type": "BUY",
      "item": "Artichoke",
      "quantity": 20,
      "price_text": "0.207 SFL",
      "price": 0.207,
      "counterparty": "Dragonsx",
      "farm_id": "-",
      "trade_id": "b8b76270"
    },
    {
      "date": "2026-01-29",
      "time": "06:08 AM",
      "type": "BUY",
      "item": "Artichoke",
      "quantity": 20,
      "price_text": "0.207 SFL",
      "price": 0.207,
      "counterparty": "Dragonsx",
      "farm_id": "-",
      "trade_id": "da06b9be"
    },
    {
      "date": "2026-01-29",
      "time": "06:04 AM",
      "type": "BUY",
      "item": "Broccoli",
      "quantity": 300,
      "price_text": "0.9868 SFL",
      "price": 0.9868,
      "counterparty": "ManhTrang",
      "farm_id": "-",
      "trade_id": "cdd521ef"
    },
    {
      "date": "2026-01-29",
      "time": "06:03 AM",
      "type": "BUY",
      "item": "Broccoli",
      "quantity": 500,
      "price_text": "1.6437 SFL",
      "price": 1.6437,
      "counterparty": "Houlala",
      "farm_id": "-",
      "trade_id": "1779c165"
    },
    {
      "date": "2026-01-29",
      "time": "06:03 AM",
      "type": "BUY",
      "item": "Broccoli",
      "quantity": 500,
      "price_text": "1.6437 SFL",
      "price": 1.6437,
      "counterparty": "Houlala",
      "farm_id": "-",
      "trade_id": "6a10afbd"
    },
    {
      "date": "2026-01-29",
      "time": "06:03 AM",
      "type": "BUY",
      "item": "Broccoli",
      "quantity": 500,
      "price_text": "1.6436 SFL",
      "price": 1.6436,
      "counterparty": "Elisan",
      "farm_id": "-",
      "trade_id": "6fdcb8ff"
    },
    {
      "date": "2026-01-29",
      "time": "06:02 AM",
      "type": "BUY",
      "item": "Broccoli",
      "quantity": 500,
      "price_text": "1.6435 SFL",
      "price": 1.6435,
      "counterparty": "maggotman",
      "farm_id": "-",
      "trade_id": "a52d1d73"
    },
    {
      "date": "2026-01-29",
      "time": "06:02 AM",
      "type": "BUY",
      "item": "Gold",
      "quantity": 12,
      "price_text": "3 SFL",
      "price": 3.0,
      "counterparty": "CARAIBRENIN",
      "farm_id": "-",
      "trade_id": "9b806b0b"
    },
    {
      "date": "2026-01-29",
      "time": "06:02 AM",
      "type": "BUY",
      "item": "Yam",
      "quantity": 500,
      "price_text": "1.4713 SFL",
      "price": 1.4713,
      "counterparty": "Elisan",
      "farm_id": "-",
      "trade_id": "fa0f2077"
    },
    {
      "date": "2026-01-29",
      "time": "06:02 AM",
      "type": "BUY",
      "item": "Yam",
      "quantity": 1000,
      "price_text": "2.9428 SFL",
      "price": 2.9428,
      "counterparty": "Vitt0c",
      "farm_id": "-",
      "trade_id": "e076d200"
    },
    {
      "date": "2026-01-29",
      "time": "05:19 AM",
      "type": "BUY",
      "item": "Milk",
      "quantity": 6,
      "price_text": "0.771 SFL",
      "price": 0.771,
      "counterparty": "Surel",
      "farm_id": "-",
      "trade_id": "ce740df9"
    },
    {
      "date": "2026-01-29",
      "time": "05:19 AM",
      "type": "BUY",
      "item": "Milk",
      "quantity": 5,
      "price_text": "0.642 SFL",
      "price": 0.642,
      "counterparty": "Biiel",
      "farm_id": "-",
      "trade_id": "59032911"
    },
    {
      "date": "2026-01-29",
      "time": "04:02 AM",
      "type": "BUY",
      "item": "Milk",
      "quantity": 38,
      "price_text": "4.56 SFL",
      "price": 4.56,
      "counterparty": "Chadtzy",
      "farm_id": "-",
      "trade_id": "4ab14311"
    }
  ],
  "sells": [
    {
      "date": "2026-01-31",
      "time": "02:37 PM",
      "type": "SELL",
      "item": "Yam",
      "quantity": 1000,
      "price_text": "2.79 SFL",
      "price": 2.79,
      "counterparty": "maebe",
      "farm_id": "-",
      "trade_id": "9ad66330"
    },
    {
      "date": "2026-01-31",
      "time": "02:22 PM",
      "type": "SELL",
      "item": "Yam",
      "quantity": 400,
      "price_text": "1.11 SFL",
      "price": 1.11,
      "counterparty": "vahaboy",
      "farm_id": "-",
      "trade_id": "ea38a2cb"
    },
    {
      "date": "2026-01-31",
      "time": "01:52 PM",
      "type": "SELL",
      "item": "Sunflower",
      "quantity": 4000,
      "price_text": "1.08 SFL",
      "price": 1.08,
      "counterparty": "Guilhem",
      "farm_id": "-",
      "trade_id": "2438a9bb"
    },
    {
      "date": "2026-01-31",
      "time": "05:43 AM",
      "type": "SELL",
      "item": "Potato",
      "quantity": 3000,
      "price_text": "0.899 SFL",
      "price": 0.899,
      "counterparty": "Lavinya",
      "farm_id": "-",
      "trade_id": "234be378"
    },
    {
      "date": "2026-01-31",
      "time": "05:43 AM",
      "type": "SELL",
      "item": "Potato",
      "quantity": 3000,
      "price_text": "0.899 SFL",
      "price": 0.899,
      "counterparty": "Lavinya",
      "farm_id": "-",
      "trade_id": "ec071e77"
    },
    {
      "date": "2026-01-31",
      "time": "05:43 AM",
      "type": "SELL",
      "item": "Potato",
      "quantity": 3000,
      "price_text": "0.899 SFL",
      "price": 0.899,
      "counterparty": "Lavinya",
      "farm_id": "-",
      "trade_id": "2e3b4f8c"
    },
    {
      "date": "2026-01-31",
      "time": "04:43 AM",
      "type": "SELL",
      "item": "Onion",
      "quantity": 200,
      "price_text": "2.05 SFL",
      "price": 2.05,
      "counterparty": "Ayz",
      "farm_id": "-",
      "trade_id": "eb8443b1"
    },
    {
      "date": "2026-01-31",
      "time": "04:29 AM",
      "type": "SELL",
      "item": "Onion",
      "quantity": 200,
      "price_text": "2.05 SFL",
      "price": 2.05,
      "counterparty": "rocy",
      "farm_id": "-",
      "trade_id": "5c6c75f4"
    },
    {
      "date": "2026-01-31",
      "time": "04:29 AM",
      "type": "SELL",
      "item": "Onion",
      "quantity": 200,
      "price_text": "2.05 SFL",
      "price": 2.05,
      "counterparty": "rocy",
      "farm_id": "-",
      "trade_id": "529431c2"
    },
    {
      "date": "2026-01-31",
      "time": "04:29 AM",
      "type": "SELL",
      "item": "Onion",
      "quantity": 85,
      "price_text": "0.871 SFL",
      "price": 0.871,
      "counterparty": "rocy",
      "farm_id": "-",
      "trade_id": "6160e7ab"
    },
    {
      "date": "2026-01-31",
      "time": "04:20 AM",
      "type": "SELL",
      "item": "Wheat",
      "quantity": 200,
      "price_text": "2.932 SFL",
      "price": 2.932,
      "counterparty": "rocy",
      "farm_id": "-",
      "trade_id": "80be2d5b"
    },
    {
      "date": "2026-01-31",
      "time": "04:13 AM",
      "type": "SELL",
      "item": "Potato",
      "quantity": 3000,
      "price_text": "0.899 SFL",
      "price": 0.899,
      "counterparty": "Sunflowes288",
      "farm_id": "-",
      "trade_id": "50f3a781"
    },
    {
      "date": "2026-01-31",
      "time": "04:01 AM",
      "type": "SELL",
      "item": "Sunflower",
      "quantity": 4000,
      "price_text": "1.07 SFL",
      "price": 1.07,
      "counterparty": "homero",
      "farm_id": "-",
      "trade_id": "bce30b7f"
    },
    {
      "date": "2026-01-31",
      "time": "04:00 AM",
      "type": "SELL",
      "item": "Wheat",
      "quantity": 200,
      "price_text": "2.932 SFL",
      "price": 2.932,
      "counterparty": "Noeta",
      "farm_id": "-",
      "trade_id": "00c94089"
    },
    {
      "date": "2026-01-31",
      "time": "04:00 AM",
      "type": "SELL",
      "item": "Sunflower",
      "quantity": 4000,
      "price_text": "1.07 SFL",
      "price": 1.07,
      "counterparty": "Harck",
      "farm_id": "-",
      "trade_id": "9de5a6d1"
    },
    {
      "date": "2026-01-31",
      "time": "03:59 AM",
      "type": "SELL",
      "item": "Sunflower",
      "quantity": 4000,
      "price_text": "1.07 SFL",
      "price": 1.07,
      "counterparty": "khatun",
      "farm_id": "-",
      "trade_id": "5fe3cf2a"
    },
    {
      "date": "2026-01-31",
      "time": "03:57 AM",
      "type": "SELL",
      "item": "Wheat",
      "quantity": 200,
      "price_text": "2.932 SFL",
      "price": 2.932,
      "counterparty": "Adrore",
      "farm_id": "-",
      "trade_id": "b302d9f1"
    },
    {
      "date": "2026-01-31",
      "time": "03:50 AM",
      "type": "SELL",
      "item": "Sunflower",
      "quantity": 4000,
      "price_text": "1.07 SFL",
      "price": 1.07,
      "counterparty": "Basti11",
      "farm_id": "-",
      "trade_id": "fda461d4"
    },
    {
      "date": "2026-01-31",
      "time": "03:50 AM",
      "type": "SELL",
      "item": "Sunflower",
      "quantity": 4000,
      "price_text": "1.07 SFL",
      "price": 1.07,
      "counterparty": "Dekcu",
      "farm_id": "-",
      "trade_id": "96a05b0d"
    },
    {
      "date": "2026-01-31",
      "time": "03:48 AM",
      "type": "SELL",
      "item": "Olive",
      "quantity": 5,
      "price_text": "2.416 SFL",
      "price": 2.416,
      "counterparty": "BabyPain",
      "farm_id": "-",
      "trade_id": "76ca3584"
    },
    {
      "date": "2026-01-31",
      "time": "03:48 AM",
      "type": "SELL",
      "item": "Iron",
      "quantity": 50,
      "price_text": "3.154 SFL",
      "price": 3.154,
      "counterparty": "Cheamigo",
      "farm_id": "-",
      "trade_id": "0ea54e4c"
    },
    {
      "date": "2026-01-31",
      "time": "03:44 AM",
      "type": "SELL",
      "item": "Olive",
      "quantity": 5,
      "price_text": "2.416 SFL",
      "price": 2.416,
      "counterparty": "mauza",
      "farm_id": "-",
      "trade_id": "ccf1a214"
    },
    {
      "date": "2026-01-31",
      "time": "03:43 AM",
      "type": "SELL",
      "item": "Gold",
      "quantity": 10,
      "price_text": "2.499 SFL",
      "price": 2.499,
      "counterparty": "Chalee",
      "farm_id": "-",
      "trade_id": "7e3bab04"
    },
    {
      "date": "2026-01-31",
      "time": "03:41 AM",
      "type": "SELL",
      "item": "Olive",
      "quantity": 5,
      "price_text": "2.02 SFL",
      "price": 2.02,
      "counterparty": "Entropia",
      "farm_id": "-",
      "trade_id": "b37d2930"
    },
    {
      "date": "2026-01-31",
      "time": "03:41 AM",
      "type": "SELL",
      "item": "Olive",
      "quantity": 5,
      "price_text": "2.021 SFL",
      "price": 2.021,
      "counterparty": "DannyMP",
      "farm_id": "-",
      "trade_id": "f134952b"
    },
    {
      "date": "2026-01-31",
      "time": "12:26 AM",
      "type": "SELL",
      "item": "Olive",
      "quantity": 5,
      "price_text": "2.2999 SFL",
      "price": 2.2999,
      "counterparty": "LunhaK",
      "farm_id": "-",
      "trade_id": "29a0ea28"
    },
    {
      "date": "2026-01-31",
      "time": "12:25 AM",
      "type": "SELL",
      "item": "Olive",
      "quantity": 5,
      "price_text": "2.2999 SFL",
      "price": 2.2999,
      "counterparty": "Lva",
      "farm_id": "-",
      "trade_id": "329fdebf"
    },
    {
      "date": "2026-01-31",
      "time": "12:15 AM",
      "type": "SELL",
      "item": "Olive",
      "quantity": 5,
      "price_text": "2.2999 SFL",
      "price": 2.2999,
      "counterparty": "loat",
      "farm_id": "-",
      "trade_id": "5b4acfb7"
    },
    {
      "date": "2026-01-30",
      "time": "05:05 PM",
      "type": "SELL",
      "item": "Olive",
      "quantity": 5,
      "price_text": "1.9513 SFL",
      "price": 1.9513,
      "counterparty": "BabyRaccoon",
      "farm_id": "-",
      "trade_id": "75407aab"
    },
    {
      "date": "2026-01-30",
      "time": "12:44 PM",
      "type": "SELL",
      "item": "Gold",
      "quantity": 10,
      "price_text": "2.399 SFL",
      "price": 2.399,
      "counterparty": "LalangostA",
      "farm_id": "-",
      "trade_id": "653a88d7"
    },
    {
      "date": "2026-01-30",
      "time": "12:36 PM",
      "type": "SELL",
      "item": "Carrot",
      "quantity": 500,
      "price_text": "0.85 SFL",
      "price": 0.85,
      "counterparty": "Nancy",
      "farm_id": "-",
      "trade_id": "278fda66"
    },
    {
      "date": "2026-01-30",
      "time": "12:35 PM",
      "type": "SELL",
      "item": "Gold",
      "quantity": 10,
      "price_text": "2.399 SFL",
      "price": 2.399,
      "counterparty": "WMW",
      "farm_id": "-",
      "trade_id": "2e7e1b95"
    },
    {
      "date": "2026-01-30",
      "time": "12:33 PM",
      "type": "SELL",
      "item": "Yam",
      "quantity": 900,
      "price_text": "2.59 SFL",
      "price": 2.59,
      "counterparty": "Tang170",
      "farm_id": "-",
      "trade_id": "456c17f7"
    },
    {
      "date": "2026-01-30",
      "time": "12:30 PM",
      "type": "SELL",
      "item": "Iron",
      "quantity": 80,
      "price_text": "5 SFL",
      "price": 5.0,
      "counterparty": "Jorjgvara",
      "farm_id": "-",
      "trade_id": "5ddedbf1"
    },
    {
      "date": "2026-01-30",
      "time": "05:48 AM",
      "type": "SELL",
      "item": "Gold",
      "quantity": 10,
      "price_text": "2.41 SFL",
      "price": 2.41,
      "counterparty": "calabazin",
      "farm_id": "-",
      "trade_id": "1165b0b4"
    },
    {
      "date": "2026-01-30",
      "time": "02:43 AM",
      "type": "SELL",
      "item": "Olive",
      "quantity": 5,
      "price_text": "2.2999 SFL",
      "price": 2.2999,
      "counterparty": "Muziboo",
      "farm_id": "-",
      "trade_id": "74063d3a"
    },
    {
      "date": "2026-01-30",
      "time": "01:13 AM",
      "type": "SELL",
      "item": "Iron",
      "quantity": 60,
      "price_text": "3.8 SFL",
      "price": 3.8,
      "counterparty": "INN",
      "farm_id": "-",
      "trade_id": "46ec0733"
    },
    {
      "date": "2026-01-29",
      "time": "05:18 PM",
      "type": "SELL",
      "item": "Gold",
      "quantity": 15,
      "price_text": "3.58 SFL",
      "price": 3.58,
      "counterparty": "Lodwig",
      "farm_id": "-",
      "trade_id": "2ce329a6"
    },
    {
      "date": "2026-01-29",
      "time": "02:07 PM",
      "type": "SELL",
      "item": "Yam",
      "quantity": 1000,
      "price_text": "2.91 SFL",
      "price": 2.91,
      "counterparty": "BintangKecil",
      "farm_id": "-",
      "trade_id": "dbb02a39"
    },
    {
      "date": "2026-01-29",
      "time": "09:21 AM",
      "type": "SELL",
      "item": "Barley",
      "quantity": 100,
      "price_text": "2.215 SFL",
      "price": 2.215,
      "counterparty": "TvoiOtets",
      "farm_id": "-",
      "trade_id": "ef7a5266"
    },
    {
      "date": "2026-01-29",
      "time": "09:13 AM",
      "type": "SELL",
      "item": "Olive",
      "quantity": 5,
      "price_text": "1.8756 SFL",
      "price": 1.8756,
      "counterparty": "KanaXan",
      "farm_id": "-",
      "trade_id": "a8e7e8fe"
    },
    {
      "date": "2026-01-29",
      "time": "09:12 AM",
      "type": "SELL",
      "item": "Yam",
      "quantity": 600,
      "price_text": "1.764 SFL",
      "price": 1.764,
      "counterparty": "Aydan",
      "farm_id": "-",
      "trade_id": "c898ab37"
    },
    {
      "date": "2026-01-29",
      "time": "06:18 AM",
      "type": "SELL",
      "item": "Kale",
      "quantity": 100,
      "price_text": "2.199 SFL",
      "price": 2.199,
      "counterparty": "Bourbon",
      "farm_id": "-",
      "trade_id": "e609f66c"
    },
    {
      "date": "2026-01-29",
      "time": "06:16 AM",
      "type": "SELL",
      "item": "Carrot",
      "quantity": 800,
      "price_text": "1.5 SFL",
      "price": 1.5,
      "counterparty": "phuong1991",
      "farm_id": "-",
      "trade_id": "66607f28"
    },
    {
      "date": "2026-01-29",
      "time": "06:16 AM",
      "type": "SELL",
      "item": "Iron",
      "quantity": 55,
      "price_text": "3.46 SFL",
      "price": 3.46,
      "counterparty": "Organicboom",
      "farm_id": "-",
      "trade_id": "a9519b4e"
    },
    {
      "date": "2026-01-29",
      "time": "06:15 AM",
      "type": "SELL",
      "item": "Blueberry",
      "quantity": 100,
      "price_text": "1.84 SFL",
      "price": 1.84,
      "counterparty": "Detectiv",
      "farm_id": "-",
      "trade_id": "6ef84195"
    },
    {
      "date": "2026-01-29",
      "time": "06:00 AM",
      "type": "SELL",
      "item": "Obsidian",
      "quantity": 1,
      "price_text": "19.64 SFL",
      "price": 19.64,
      "counterparty": "Zed",
      "farm_id": "-",
      "trade_id": "61a85407"
    },
    {
      "date": "2026-01-29",
      "time": "03:16 AM",
      "type": "SELL",
      "item": "Eggplant",
      "quantity": 200,
      "price_text": "1.61 SFL",
      "price": 1.61,
      "counterparty": "JFK97jinxer",
      "farm_id": "-",
      "trade_id": "6864c864"
    }
  ],
  "last_updated": null,
  "stats": {
    "total_buys": 90,
    "total_sells": 48,
    "buy_volume": 124.82319999999997,
    "sell_volume": 117.4615,
    "gross_profit": -7.361699999999971,
    "avg_buy_price": 1.3869244444444442,
    "avg_sell_price": 2.447114583333333,
    "most_traded_items": {},
    "recent_activity": [
      {
        "type": "BUY",
        "item": "Tomato",
        "quantity": 100,
        "price": 0.4901,
        "date": "2026-01-31",
        "time": "04:11 PM",
        "username": "droid"
      },
      {
        "type": "BUY",
        "item": "Stone",
        "quantity": 30,
        "price": 0.4735,
        "date": "2026-01-31",
        "time": "04:10 PM",
        "username": "droid"
      },
      {
        "type": "BUY",
        "item": "Milk",
        "quantity": 30,
        "price": 3.762,
        "date": "2026-01-31",
        "time": "03:26 PM",
        "username": "droid"
      },
      {
        "type": "BUY",
        "item": "Honey",
        "quantity": 18,
        "price": 1.0439,
        "date": "2026-01-31",
        "time": "03:26 PM",
        "username": "droid"
      },
      {
        "type": "BUY",
        "item": "Tomato",
        "quantity": 50,
        "price": 0.2453,
        "date": "2026-01-31",
        "time": "03:25 PM",
        "username": "droid"
      },
      {
        "type": "BUY",
        "item": "Milk",
        "quantity": 25,
        "price": 3.12,
        "date": "2026-01-31",
        "time": "02:49 PM"
      },
      {
        "type": "BUY",
        "item": "Stone",
        "quantity": 43,
        "price": 0.6837,
        "date": "2026-01-31",
        "time": "11:08 AM"
      },
      {
        "type": "BUY",
        "item": "Honey",
        "quantity": 10,
        "price": 0.6383,
        "date": "2026-01-31",
        "time": "10:29 AM"
      },
      {
        "type": "BUY",
        "item": "Milk",
        "quantity": 45,
        "price": 5.5113,
        "date": "2026-01-31",
        "time": "08:55 AM"
      },
      {
        "type": "BUY",
        "item": "Parsnip",
        "quantity": 50,
        "price": 0.9999,
        "date": "2026-01-31",
        "time": "08:26 AM"
      },
      {
        "type": "BUY",
        "item": "Beetroot",
        "quantity": 100,
        "price": 0.6799,
        "date": "2026-01-31",
        "time": "08:25 AM"
      },
      {
        "type": "BUY",
        "item": "Honey",
        "quantity": 23,
        "price": 1.3294,
        "date": "2026-01-31",
        "time": "05:56 AM"
      },
      {
        "type": "BUY",
        "item": "Milk",
        "quantity": 100,
        "price": 12.2999,
        "date": "2026-01-31",
        "time": "05:21 AM"
      },
      {
        "type": "BUY",
        "item": "Milk",
        "quantity": 13,
        "price": 1.5989,
        "date": "2026-01-31",
        "time": "05:20 AM"
      },
      {
        "type": "BUY",
        "item": "Milk",
        "quantity": 13,
        "price": 1.5989,
        "date": "2026-01-31",
        "time": "05:20 AM"
      },
      {
        "type": "BUY",
        "item": "Milk",
        "quantity": 10,
        "price": 1.2299,
        "date": "2026-01-31",
        "time": "05:20 AM"
      },
      {
        "type": "BUY",
        "item": "Wool",
        "quantity": 19,
        "price": 1.124,
        "date": "2026-01-31",
        "time": "03:53 AM"
      },
      {
        "type": "BUY",
        "item": "Leather",
        "quantity": 50,
        "price": 6.175,
        "date": "2026-01-31",
        "time": "03:47 AM"
      },
      {
        "type": "BUY",
        "item": "Milk",
        "quantity": 9,
        "price": 1.1115,
        "date": "2026-01-31",
        "time": "03:42 AM"
      },
      {
        "type": "BUY",
        "item": "Milk",
        "quantity": 17,
        "price": 2.0995,
        "date": "2026-01-31",
        "time": "03:42 AM"
      }
    ],
    "profit_margin": -5.897701709297609,
    "most_bought_items": {
      "Broccoli": 2300,
      "Yam": 1650,
      "Carrot": 600,
      "Stone": 596,
      "Milk": 472,
      "Tomato": 350,
      "Artichoke": 291,
      "Lemon": 175,
      "Parsnip": 150,
      "Leather": 114
    },
    "most_sold_items": {
      "Sunflower": 24000,
      "Potato": 12000,
      "Yam": 3900,
      "Carrot": 1300,
      "Onion": 685,
      "Wheat": 600,
      "Iron": 245,
      "Eggplant": 200,
      "Barley": 100,
      "Kale": 100
    }
  },
  "active_listings": [
    {
      "id": "c3bfe565",
      "item": "Oil Gallon",
      "quantity": 1,
      "price": 3997,
      "created_at": 1760943255403,
      "collection": "wearables",
      "trade_type": "onchain"
    },
    {
      "id": "c6d4e3ac",
      "item": "Normal Fish Hat",
      "quantity": 1,
      "price": 67.99,
      "created_at": 1764907746297,
      "collection": "wearables",
      "trade_type": "instant"
    },
    {
      "id": "e5ac830f",
      "item": "Crimstone Boots",
      "quantity": 1,
      "price": 19,
      "created_at": 1766039934084,
      "collection": "wearables",
      "trade_type": "instant"
    },
    {
      "id": "1e6c6485",
      "item": "Iron Idol",
      "quantity": 1,
      "price": 5999,
      "created_at": 1767644224366,
      "collection": "collectibles",
      "trade_type": "onchain"
    },
    {
      "id": "cef3abc4",
      "item": "Eggplant",
      "quantity": 500,
      "price": 4.85,
      "created_at": 1769656189516,
      "collection": "collectibles",
      "trade_type": "instant"
    }
  ],
  "active_offers": [],
  "inventory": {
    "crops": {
      "Sunflower": 7564.535199987208,
      "Potato": 4016.0014999946266,
      "Pumpkin": 111.6692,
      "Carrot": 352.6097,
      "Cabbage": 52.5857,
      "Beetroot": 28.455600000000064,
      "Cauliflower": 14.750899999999925,
      "Parsnip": 11.118999999999927,
      "Radish": 277.2946999999998,
      "Wheat": 268.0782999999989,
      "Kale": 65.2209999999999,
      "Eggplant": 758.8689,
      "Corn": 0.0301000000000001,
      "Soybean": 111.4219,
      "Rice": 0.991,
      "Olive": 2.1548,
      "Barley": 40.73979999999994,
      "Rhubarb": 96.35,
      "Zucchini": 588.6496,
      "Yam": 638.1633,
      "Broccoli": 115.2199,
      "Pepper": 46.7,
      "Onion": 0.7929000000000271,
      "Turnip": 21.296100000000017,
      "Artichoke": 25.00610000000002
    },
    "fruits": {
      "Apple": 38.0000000000005,
      "Blueberry": 3.000000000005413,
      "Orange": 0.8000000000008347,
      "Banana": 0.5000000000007112,
      "Grape": 1.9,
      "Tomato": 81.40000000000063,
      "Lemon": 18.300000000001077,
      "Duskberry": 6e-15,
      "Lunara": 0.9000000000000099,
      "Celestine": 2.4000000000000252
    },
    "resources": {
      "Wood": 175.27,
      "Stone": 6.04,
      "Iron": 115.38,
      "Gold": 4.51,
      "Obsidian": 10.2,
      "Crimstone": 8.0
    }
  }
}